liffile/__init__.py
liffile/__main__.py
liffile/liffile.py
liffile/py.typed
liffile-2026.1.14.dist-info/licenses/LICENSE
liffile-2026.1.14.dist-info/METADATA
liffile-2026.1.14.dist-info/WHEEL
liffile-2026.1.14.dist-info/entry_points.txt
liffile-2026.1.14.dist-info/top_level.txt
liffile-2026.1.14.dist-info/RECORD
